{
  "game" : {
    "player1" : {
      "name" : "asd",
      "karten" : [ {
        "cardv" : "Y+"
      }, {
        "cardv" : "G+"
      }, {
        "cardv" : "G3"
      }, {
        "cardv" : "G6"
      }, {
        "cardv" : "B0"
      }, {
        "cardv" : "Y6"
      }, {
        "cardv" : "BS"
      } ],
      "kartenzahl" : 7,
      "placed" : false,
      "png_ind" : [ {
        "card_png" : "cards/yellow_+2.png",
        "index" : "0"
      }, {
        "card_png" : "cards/green_+2.png",
        "index" : "1"
      }, {
        "card_png" : "cards/green_3.png",
        "index" : "2"
      }, {
        "card_png" : "cards/green_6.png",
        "index" : "3"
      }, {
        "card_png" : "cards/blue_0.png",
        "index" : "4"
      }, {
        "card_png" : "cards/yellow_6.png",
        "index" : "5"
      }, {
        "card_png" : "cards/blue_skip.png",
        "index" : "6"
      } ]
    },
    "player2" : {
      "name" : "asd",
      "karten" : [ {
        "cardv" : "G0"
      }, {
        "cardv" : "R7"
      }, {
        "cardv" : "B3"
      }, {
        "cardv" : "R4"
      }, {
        "cardv" : "B5"
      }, {
        "cardv" : "YS"
      }, {
        "cardv" : "Y9"
      } ],
      "kartenzahl" : 7,
      "placed" : false,
      "png_ind" : [ {
        "card_png" : "cards/green_0.png",
        "index" : "0"
      }, {
        "card_png" : "cards/red_7.png",
        "index" : "1"
      }, {
        "card_png" : "cards/blue_3.png",
        "index" : "2"
      }, {
        "card_png" : "cards/red_4.png",
        "index" : "3"
      }, {
        "card_png" : "cards/blue_5.png",
        "index" : "4"
      }, {
        "card_png" : "cards/yellow_skip.png",
        "index" : "5"
      }, {
        "card_png" : "cards/yellow_9.png",
        "index" : "6"
      } ]
    },
    "currentstate" : "between21State",
    "ERROR" : 0,
    "cardstack" : [ {
      "cardv" : "R8",
      "value" : 2
    }, {
      "cardv" : "Y5",
      "value" : 2
    }, {
      "cardv" : "R7",
      "value" : 1
    }, {
      "cardv" : "Y+",
      "value" : 1
    }, {
      "cardv" : "B3",
      "value" : 1
    }, {
      "cardv" : "R+",
      "value" : 2
    }, {
      "cardv" : "R6",
      "value" : 2
    }, {
      "cardv" : "Y9",
      "value" : 1
    }, {
      "cardv" : "B0",
      "value" : 1
    }, {
      "cardv" : "XX",
      "value" : 2
    }, {
      "cardv" : "Y4",
      "value" : 2
    }, {
      "cardv" : "G4",
      "value" : 2
    }, {
      "cardv" : "B7",
      "value" : 2
    }, {
      "cardv" : "G3",
      "value" : 1
    }, {
      "cardv" : "GC",
      "value" : 2
    }, {
      "cardv" : "G2",
      "value" : 2
    }, {
      "cardv" : "RS",
      "value" : 2
    }, {
      "cardv" : "BC",
      "value" : 2
    }, {
      "cardv" : "R2",
      "value" : 2
    }, {
      "cardv" : "Y6",
      "value" : 1
    }, {
      "cardv" : "B5",
      "value" : 1
    }, {
      "cardv" : "G8",
      "value" : 2
    }, {
      "cardv" : "R0",
      "value" : 2
    }, {
      "cardv" : "Y1",
      "value" : 2
    }, {
      "cardv" : "B1",
      "value" : 2
    }, {
      "cardv" : "Y8",
      "value" : 2
    }, {
      "cardv" : "R1",
      "value" : 1
    }, {
      "cardv" : "G+",
      "value" : 1
    }, {
      "cardv" : "G1",
      "value" : 2
    }, {
      "cardv" : "YS",
      "value" : 1
    }, {
      "cardv" : "B+",
      "value" : 2
    }, {
      "cardv" : "Y7",
      "value" : 2
    }, {
      "cardv" : "B6",
      "value" : 2
    }, {
      "cardv" : "G9",
      "value" : 2
    }, {
      "cardv" : "R9",
      "value" : 2
    }, {
      "cardv" : "R3",
      "value" : 2
    }, {
      "cardv" : "R5",
      "value" : 2
    }, {
      "cardv" : "B4",
      "value" : 2
    }, {
      "cardv" : "YC",
      "value" : 2
    }, {
      "cardv" : "RC",
      "value" : 2
    }, {
      "cardv" : "Y2",
      "value" : 2
    }, {
      "cardv" : "G7",
      "value" : 2
    }, {
      "cardv" : "GS",
      "value" : 2
    }, {
      "cardv" : "R4",
      "value" : 1
    }, {
      "cardv" : "Y0",
      "value" : 2
    }, {
      "cardv" : "Y3",
      "value" : 2
    }, {
      "cardv" : "G5",
      "value" : 2
    }, {
      "cardv" : "G0",
      "value" : 1
    }, {
      "cardv" : "G6",
      "value" : 1
    }, {
      "cardv" : "BS",
      "value" : 1
    }, {
      "cardv" : "B2",
      "value" : 2
    }, {
      "cardv" : "WC",
      "value" : 2
    }, {
      "cardv" : "B8",
      "value" : 2
    }, {
      "cardv" : "B9",
      "value" : 2
    }, {
      "cardv" : "+4",
      "value" : 2
    } ],
    "midCard" : {
      "name" : "midcard",
      "karten" : [ {
        "cardv" : "R1"
      } ],
      "placed" : false,
      "png_ind" : [ {
        "card_png" : "cards/red_1.png",
        "index" : "0"
      } ]
    },
    "winner" : -1
  }
}